istsosproto/__init__.py
istsosproto/databasic_grpc.py
istsosproto/databasic_pb2.py
istsosproto/dataprofile_grpc.py
istsosproto/dataprofile_pb2.py
istsosproto/dataraster_grpc.py
istsosproto/dataraster_pb2.py
istsosproto/metadata_grpc.py
istsosproto/metadata_pb2.py
istsosproto/query_grpc.py
istsosproto/query_pb2.py
istsosproto/spatial_grpc.py
istsosproto/spatial_pb2.py
istsos_proto-0.0.1b3.dist-info/METADATA
istsos_proto-0.0.1b3.dist-info/WHEEL
istsos_proto-0.0.1b3.dist-info/top_level.txt
istsos_proto-0.0.1b3.dist-info/RECORD
